cvfbbbb/__init__.py
cvfbbbb/core.py
cvfbbbb/log.py
cvfbbbb-0.1.1.dist-info/METADATA
cvfbbbb-0.1.1.dist-info/WHEEL
cvfbbbb-0.1.1.dist-info/top_level.txt
cvfbbbb-0.1.1.dist-info/RECORD
